doubleagent/__init__.py
doubleagent/alldel.py
doubleagent/alpacomposite.py
doubleagent/cases.py
doubleagent/errorboy.py
doubleagent/horizonpaste.py
doubleagent/listsplit.py
doubleagent/ll2l.py
doubleagent/mix.py
doubleagent/multiplesplit.py
doubleagent/overlapchecker.py
doubleagent/picklemaker.py
doubleagent/picklereader.py
doubleagent/pinset.py
doubleagent/readfile.py
doubleagent/rectangularcroplocation.py
doubleagent/removeAlpha.py
doubleagent/report.py
doubleagent/rightreplace.py
doubleagent/roundimage.py
doubleagent/s2l.py
doubleagent/seleupdate.py
doubleagent/speedcases.py
doubleagent/sublist.py
doubleagent/txt2crop.py
doubleagent/unanimous.py
doubleagent/verticalpaste.py
doubleagent/whiterbg.py
doubleagent-1.64.dist-info/METADATA
doubleagent-1.64.dist-info/WHEEL
doubleagent-1.64.dist-info/top_level.txt
doubleagent-1.64.dist-info/RECORD
