Metadata-Version: 2.1
Name: doubleagent
Version: 1.64
Summary: for me
Home-page: 
Author: complexplayer
Author-email: didutc@gmail.com
License: MIT
Classifier: Programming Language :: Python :: 3
Classifier: License :: OSI Approved :: MIT License
Classifier: Operating System :: OS Independent
